{
  "confirmed": 0,
  "elapsed": "51m10.672255041s",
  "listedOnly": 1,
  "missed": 91,
  "platform": "clubcaddie",
  "results": [
    {
      "input": "Aguila Golf Course",
      "city": "Phoenix",
      "status": "miss",
      "slugsTried": [
        "aguilagolfcourse.com",
        "aguilagolf.com",
        "aguilagolfclub.com",
        "aguilacc.com",
        "aguila.com",
        "aguila-golf-course.com",
        "aguila-golf.com",
        "aguila-golf-club.com",
        "playaguila.com",
        "golfaguila.com",
        "aguilagolfcourse.org",
        "aguilagolf.org",
        "aguila-golf-course.org",
        "aguilagolfcourse.net"
      ]
    },
    {
      "input": "Cave Creek Golf Course",
      "city": "Phoenix",
      "status": "miss",
      "slugsTried": [
        "cavecreekgolfcourse.com",
        "cavecreekgolf.com",
        "cavecreekgolfclub.com",
        "cavecreekcc.com",
        "cavecreek.com",
        "cave-creek-golf-course.com",
        "cave-creek-golf.com",
        "cave-creek-golf-club.com",
        "playcavecreek.com",
        "playcave-creek.com",
        "golfcavecreek.com",
        "cavecreekgolfcourse.org",
        "cavecreekgolf.org",
        "cave-creek-golf-course.org",
        "cavecreekgolfcourse.net"
      ]
    },
    {
      "input": "Encanto Golf Course",
      "city": "Phoenix",
      "status": "miss",
      "slugsTried": [
        "encantogolfcourse.com",
        "encantogolf.com",
        "encantogolfclub.com",
        "encantocc.com",
        "encanto.com",
        "encanto-golf-course.com",
        "encanto-golf.com",
        "encanto-golf-club.com",
        "playencanto.com",
        "golfencanto.com",
        "encantogolfcourse.org",
        "encantogolf.org",
        "encanto-golf-course.org",
        "encantogolfcourse.net"
      ]
    },
    {
      "input": "Encanto 9-Hole Golf Course",
      "city": "Phoenix",
      "status": "miss",
      "slugsTried": [
        "encanto9holegolfcourse.com",
        "encanto9holegolf.com",
        "encanto9holegolfclub.com",
        "encanto9holecc.com",
        "encanto9hole.com",
        "encanto-9-hole-golf-course.com",
        "encanto-9-hole-golf.com",
        "encanto-9-hole-golf-club.com",
        "playencanto9hole.com",
        "playencanto-9-hole.com",
        "golfencanto9hole.com",
        "encanto9holegolfcourse.org",
        "encanto9holegolf.org",
        "encanto-9-hole-golf-course.org",
        "encanto9holegolfcourse.net"
      ]
    },
    {
      "input": "Palo Verde Golf Course",
      "city": "Phoenix",
      "status": "miss",
      "slugsTried": [
        "paloverdegolfcourse.com",
        "paloverdegolf.com",
        "paloverdegolfclub.com",
        "paloverdecc.com",
        "paloverde.com",
        "palo-verde-golf-course.com",
        "palo-verde-golf.com",
        "palo-verde-golf-club.com",
        "playpaloverde.com",
        "playpalo-verde.com",
        "golfpaloverde.com",
        "paloverdegolfcourse.org",
        "paloverdegolf.org",
        "palo-verde-golf-course.org",
        "paloverdegolfcourse.net"
      ]
    },
    {
      "input": "Papago Golf Course",
      "city": "Phoenix",
      "status": "miss",
      "slugsTried": [
        "papagogolfcourse.com",
        "papagogolf.com",
        "papagogolfclub.com",
        "papagocc.com",
        "papago.com",
        "papago-golf-course.com",
        "papago-golf.com",
        "papago-golf-club.com",
        "playpapago.com",
        "golfpapago.com",
        "papagogolfcourse.org",
        "papagogolf.org",
        "papago-golf-course.org",
        "papagogolfcourse.net"
      ]
    },
    {
      "input": "Maryvale Golf Course",
      "city": "Phoenix",
      "status": "miss",
      "slugsTried": [
        "maryvalegolfcourse.com",
        "maryvalegolf.com",
        "maryvalegolfclub.com",
        "maryvalecc.com",
        "maryvale.com",
        "maryvale-golf-course.com",
        "maryvale-golf.com",
        "maryvale-golf-club.com",
        "playmaryvale.com",
        "golfmaryvale.com",
        "maryvalegolfcourse.org",
        "maryvalegolf.org",
        "maryvale-golf-course.org",
        "maryvalegolfcourse.net"
      ]
    },
    {
      "input": "Coronado Golf Course",
      "city": "Scottsdale",
      "status": "miss",
      "slugsTried": [
        "coronadogolfcourse.com",
        "coronadogolf.com",
        "coronadogolfclub.com",
        "coronadocc.com",
        "coronado.com",
        "coronado-golf-course.com",
        "coronado-golf.com",
        "coronado-golf-club.com",
        "playcoronado.com",
        "golfcoronado.com",
        "coronadogolfcourse.org",
        "coronadogolf.org",
        "coronado-golf-course.org",
        "coronadogolfcourse.net"
      ]
    },
    {
      "input": "Continental Golf Club",
      "city": "Scottsdale",
      "status": "miss",
      "slugsTried": [
        "continentalgolfclub.com",
        "continentalgolf.com",
        "continentalgolfcourse.com",
        "continentalcc.com",
        "continental.com",
        "continental-golf-club.com",
        "continental-golf.com",
        "continental-golf-course.com",
        "playcontinental.com",
        "golfcontinental.com",
        "continentalgolfclub.org",
        "continentalgolf.org",
        "continental-golf-club.org",
        "continentalgolfclub.net"
      ]
    },
    {
      "input": "Ken McDonald Golf Course",
      "city": "Tempe",
      "status": "miss",
      "slugsTried": [
        "kenmcdonaldgolfcourse.com",
        "kenmcdonaldgolf.com",
        "kenmcdonaldgolfclub.com",
        "kenmcdonaldcc.com",
        "kenmcdonald.com",
        "ken-mcdonald-golf-course.com",
        "ken-mcdonald-golf.com",
        "ken-mcdonald-golf-club.com",
        "playkenmcdonald.com",
        "playken-mcdonald.com",
        "golfkenmcdonald.com",
        "kenmcdonaldgolfcourse.org",
        "kenmcdonaldgolf.org",
        "ken-mcdonald-golf-course.org",
        "kenmcdonaldgolfcourse.net"
      ]
    },
    {
      "input": "Rolling Hills Golf Course",
      "city": "Tempe",
      "status": "miss",
      "slugsTried": [
        "rollinghillsgolfcourse.com",
        "rollinghillsgolf.com",
        "rollinghillsgolfclub.com",
        "rollinghillscc.com",
        "rollinghills.com",
        "rolling-hills-golf-course.com",
        "rolling-hills-golf.com",
        "rolling-hills-golf-club.com",
        "playrollinghills.com",
        "playrolling-hills.com",
        "golfrollinghills.com",
        "rollinghillsgolfcourse.org",
        "rollinghillsgolf.org",
        "rolling-hills-golf-course.org",
        "rollinghillsgolfcourse.net"
      ]
    },
    {
      "input": "Dobson Ranch Golf Course",
      "city": "Mesa",
      "status": "miss",
      "slugsTried": [
        "dobsonranchgolfcourse.com",
        "dobsonranchgolf.com",
        "dobsonranchgolfclub.com",
        "dobsonranchcc.com",
        "dobsonranch.com",
        "dobson-ranch-golf-course.com",
        "dobson-ranch-golf.com",
        "dobson-ranch-golf-club.com",
        "playdobsonranch.com",
        "playdobson-ranch.com",
        "golfdobsonranch.com",
        "dobsonranchgolfcourse.org",
        "dobsonranchgolf.org",
        "dobson-ranch-golf-course.org",
        "dobsonranchgolfcourse.net"
      ]
    },
    {
      "input": "Ak-Chin Southern Dunes Golf Club",
      "city": "Maricopa",
      "status": "miss",
      "slugsTried": [
        "akchinsoutherndunesgolfclub.com",
        "akchinsoutherndunesgolf.com",
        "akchinsoutherndunesgolfcourse.com",
        "akchinsoutherndunescc.com",
        "akchinsoutherndunes.com",
        "ak-chin-southern-dunes-golf-club.com",
        "ak-chin-southern-dunes-golf.com",
        "ak-chin-southern-dunes-golf-course.com",
        "playakchinsoutherndunes.com",
        "playak-chin-southern-dunes.com",
        "golfakchinsoutherndunes.com",
        "akchinsoutherndunesgolfclub.org",
        "akchinsoutherndunesgolf.org",
        "ak-chin-southern-dunes-golf-club.org",
        "akchinsoutherndunesgolfclub.net"
      ]
    },
    {
      "input": "Arizona Biltmore Golf Club",
      "city": "Phoenix",
      "status": "miss",
      "slugsTried": [
        "arizonabiltmoregolfclub.com",
        "arizonabiltmoregolf.com",
        "arizonabiltmoregolfcourse.com",
        "arizonabiltmorecc.com",
        "arizonabiltmore.com",
        "arizona-biltmore-golf-club.com",
        "arizona-biltmore-golf.com",
        "arizona-biltmore-golf-course.com",
        "playarizonabiltmore.com",
        "playarizona-biltmore.com",
        "golfarizonabiltmore.com",
        "arizonabiltmoregolfclub.org",
        "arizonabiltmoregolf.org",
        "arizona-biltmore-golf-club.org",
        "arizonabiltmoregolfclub.net"
      ]
    },
    {
      "input": "Arizona Grand Golf Course",
      "city": "Phoenix",
      "status": "miss",
      "slugsTried": [
        "arizonagrandgolfcourse.com",
        "arizonagrandgolf.com",
        "arizonagrandgolfclub.com",
        "arizonagrandcc.com",
        "arizonagrand.com",
        "arizona-grand-golf-course.com",
        "arizona-grand-golf.com",
        "arizona-grand-golf-club.com",
        "playarizonagrand.com",
        "playarizona-grand.com",
        "golfarizonagrand.com",
        "arizonagrandgolfcourse.org",
        "arizonagrandgolf.org",
        "arizona-grand-golf-course.org",
        "arizonagrandgolfcourse.net"
      ]
    },
    {
      "input": "ASU Karsten Golf Course",
      "city": "Tempe",
      "status": "miss",
      "slugsTried": [
        "asukarstengolfcourse.com",
        "asukarstengolf.com",
        "asukarstengolfclub.com",
        "asukarstencc.com",
        "asukarsten.com",
        "asu-karsten-golf-course.com",
        "asu-karsten-golf.com",
        "asu-karsten-golf-club.com",
        "playasukarsten.com",
        "playasu-karsten.com",
        "golfasukarsten.com",
        "asukarstengolfcourse.org",
        "asukarstengolf.org",
        "asu-karsten-golf-course.org",
        "asukarstengolfcourse.net"
      ]
    },
    {
      "input": "Augusta Ranch Golf Club",
      "city": "Mesa",
      "status": "miss",
      "slugsTried": [
        "augustaranchgolfclub.com",
        "augustaranchgolf.com",
        "augustaranchgolfcourse.com",
        "augustaranchcc.com",
        "augustaranch.com",
        "augusta-ranch-golf-club.com",
        "augusta-ranch-golf.com",
        "augusta-ranch-golf-course.com",
        "playaugustaranch.com",
        "playaugusta-ranch.com",
        "golfaugustaranch.com",
        "augustaranchgolfclub.org",
        "augustaranchgolf.org",
        "augusta-ranch-golf-club.org",
        "augustaranchgolfclub.net"
      ]
    },
    {
      "input": "Bear Creek Golf Complex",
      "city": "Chandler",
      "status": "miss",
      "slugsTried": [
        "bearcreekgolfcomplex.com",
        "bearcreekgolf.com",
        "bearcreekgolfclub.com",
        "bearcreekgolfcourse.com",
        "bearcreekcc.com",
        "bearcreek.com",
        "bear-creek-golf-complex.com",
        "bear-creek-golf.com",
        "bear-creek-golf-club.com",
        "bear-creek-golf-course.com",
        "playbearcreek.com",
        "playbear-creek.com",
        "golfbearcreek.com",
        "bearcreekgolfcomplex.org",
        "bearcreekgolf.org",
        "bear-creek-golf-complex.org",
        "bearcreekgolfcomplex.net"
      ]
    },
    {
      "input": "Bellair Golf Club",
      "city": "Glendale",
      "status": "miss",
      "slugsTried": [
        "bellairgolfclub.com",
        "bellairgolf.com",
        "bellairgolfcourse.com",
        "bellaircc.com",
        "bellair.com",
        "bellair-golf-club.com",
        "bellair-golf.com",
        "bellair-golf-course.com",
        "playbellair.com",
        "golfbellair.com",
        "bellairgolfclub.org",
        "bellairgolf.org",
        "bellair-golf-club.org",
        "bellairgolfclub.net"
      ]
    },
    {
      "input": "Camelback Golf Club",
      "city": "Scottsdale",
      "status": "miss",
      "slugsTried": [
        "camelbackgolfclub.com",
        "camelbackgolf.com",
        "camelbackgolfcourse.com",
        "camelbackcc.com",
        "camelback.com",
        "camelback-golf-club.com",
        "camelback-golf.com",
        "camelback-golf-course.com",
        "playcamelback.com",
        "golfcamelback.com",
        "camelbackgolfclub.org",
        "camelbackgolf.org",
        "camelback-golf-club.org",
        "camelbackgolfclub.net"
      ]
    },
    {
      "input": "Coldwater Golf Club",
      "city": "Avondale",
      "status": "miss",
      "slugsTried": [
        "coldwatergolfclub.com",
        "coldwatergolf.com",
        "coldwatergolfcourse.com",
        "coldwatercc.com",
        "coldwater.com",
        "coldwater-golf-club.com",
        "coldwater-golf.com",
        "coldwater-golf-course.com",
        "playcoldwater.com",
        "golfcoldwater.com",
        "coldwatergolfclub.org",
        "coldwatergolf.org",
        "coldwater-golf-club.org",
        "coldwatergolfclub.net"
      ]
    },
    {
      "input": "Coyote Lakes Golf Club",
      "city": "Surprise",
      "status": "miss",
      "slugsTried": [
        "coyotelakesgolfclub.com",
        "coyotelakesgolf.com",
        "coyotelakesgolfcourse.com",
        "coyotelakescc.com",
        "coyotelakes.com",
        "coyote-lakes-golf-club.com",
        "coyote-lakes-golf.com",
        "coyote-lakes-golf-course.com",
        "playcoyotelakes.com",
        "playcoyote-lakes.com",
        "golfcoyotelakes.com",
        "coyotelakesgolfclub.org",
        "coyotelakesgolf.org",
        "coyote-lakes-golf-club.org",
        "coyotelakesgolfclub.net"
      ]
    },
    {
      "input": "Desert Canyon Golf Club",
      "city": "Fountain Hills",
      "status": "miss",
      "slugsTried": [
        "desertcanyongolfclub.com",
        "desertcanyongolf.com",
        "desertcanyongolfcourse.com",
        "desertcanyoncc.com",
        "desertcanyon.com",
        "desert-canyon-golf-club.com",
        "desert-canyon-golf.com",
        "desert-canyon-golf-course.com",
        "playdesertcanyon.com",
        "playdesert-canyon.com",
        "golfdesertcanyon.com",
        "desertcanyongolfclub.org",
        "desertcanyongolf.org",
        "desert-canyon-golf-club.org",
        "desertcanyongolfclub.net"
      ]
    },
    {
      "input": "Dove Valley Ranch Golf Club",
      "city": "Cave Creek",
      "status": "miss",
      "slugsTried": [
        "dovevalleyranchgolfclub.com",
        "dovevalleyranchgolf.com",
        "dovevalleyranchgolfcourse.com",
        "dovevalleyranchcc.com",
        "dovevalleyranch.com",
        "dove-valley-ranch-golf-club.com",
        "dove-valley-ranch-golf.com",
        "dove-valley-ranch-golf-course.com",
        "playdovevalleyranch.com",
        "playdove-valley-ranch.com",
        "golfdovevalleyranch.com",
        "dovevalleyranchgolfclub.org",
        "dovevalleyranchgolf.org",
        "dove-valley-ranch-golf-club.org",
        "dovevalleyranchgolfclub.net"
      ]
    },
    {
      "input": "Eagle Mountain Golf Club",
      "city": "Fountain Hills",
      "status": "miss",
      "slugsTried": [
        "eaglemountaingolfclub.com",
        "eaglemountaingolf.com",
        "eaglemountaingolfcourse.com",
        "eaglemountaincc.com",
        "eaglemountain.com",
        "eagle-mountain-golf-club.com",
        "eagle-mountain-golf.com",
        "eagle-mountain-golf-course.com",
        "playeaglemountain.com",
        "playeagle-mountain.com",
        "golfeaglemountain.com",
        "eaglemountaingolfclub.org",
        "eaglemountaingolf.org",
        "eagle-mountain-golf-club.org",
        "eaglemountaingolfclub.net"
      ]
    },
    {
      "input": "Foothills Golf Club",
      "city": "Phoenix",
      "status": "miss",
      "slugsTried": [
        "foothillsgolfclub.com",
        "foothillsgolf.com",
        "foothillsgolfcourse.com",
        "foothillscc.com",
        "foothills.com",
        "foothills-golf-club.com",
        "foothills-golf.com",
        "foothills-golf-course.com",
        "playfoothills.com",
        "golffoothills.com",
        "foothillsgolfclub.org",
        "foothillsgolf.org",
        "foothills-golf-club.org",
        "foothillsgolfclub.net"
      ]
    },
    {
      "input": "Golf Club of Estrella",
      "city": "Goodyear",
      "status": "miss",
      "slugsTried": [
        "golfclubofestrella.com",
        "ofestrellagolf.com",
        "ofestrellagolfclub.com",
        "ofestrellagolfcourse.com",
        "ofestrellacc.com",
        "ofestrella.com",
        "golf-club-of-estrella.com",
        "of-estrella-golf.com",
        "of-estrella-golf-club.com",
        "of-estrella-golf-course.com",
        "playofestrella.com",
        "playof-estrella.com",
        "golfofestrella.com",
        "golfclubofestrella.org",
        "ofestrellagolf.org",
        "golf-club-of-estrella.org",
        "golfclubofestrella.net"
      ]
    },
    {
      "input": "Golf Club at Johnson Ranch",
      "city": "San Tan Valley",
      "status": "miss",
      "slugsTried": [
        "golfclubatjohnsonranch.com",
        "atjohnsonranchgolf.com",
        "atjohnsonranchgolfclub.com",
        "atjohnsonranchgolfcourse.com",
        "atjohnsonranchcc.com",
        "atjohnsonranch.com",
        "golf-club-at-johnson-ranch.com",
        "at-johnson-ranch-golf.com",
        "at-johnson-ranch-golf-club.com",
        "at-johnson-ranch-golf-course.com",
        "playatjohnsonranch.com",
        "playat-johnson-ranch.com",
        "golfatjohnsonranch.com",
        "golfclubatjohnsonranch.org",
        "atjohnsonranchgolf.org",
        "golf-club-at-johnson-ranch.org",
        "golfclubatjohnsonranch.net"
      ]
    },
    {
      "input": "Grand Canyon University Golf Course",
      "city": "Phoenix",
      "status": "miss",
      "slugsTried": [
        "grandcanyonuniversitygolfcourse.com",
        "grandcanyonuniversitygolf.com",
        "grandcanyonuniversitygolfclub.com",
        "grandcanyonuniversitycc.com",
        "grandcanyonuniversity.com",
        "grand-canyon-university-golf-course.com",
        "grand-canyon-university-golf.com",
        "grand-canyon-university-golf-club.com",
        "playgrandcanyonuniversity.com",
        "playgrand-canyon-university.com",
        "golfgrandcanyonuniversity.com",
        "grandcanyonuniversitygolfcourse.org",
        "grandcanyonuniversitygolf.org",
        "grand-canyon-university-golf-course.org",
        "grandcanyonuniversitygolfcourse.net"
      ]
    },
    {
      "input": "Granite Falls Golf Club",
      "city": "Surprise",
      "status": "miss",
      "slugsTried": [
        "granitefallsgolfclub.com",
        "granitefallsgolf.com",
        "granitefallsgolfcourse.com",
        "granitefallscc.com",
        "granitefalls.com",
        "granite-falls-golf-club.com",
        "granite-falls-golf.com",
        "granite-falls-golf-course.com",
        "playgranitefalls.com",
        "playgranite-falls.com",
        "golfgranitefalls.com",
        "granitefallsgolfclub.org",
        "granitefallsgolf.org",
        "granite-falls-golf-club.org",
        "granitefallsgolfclub.net"
      ]
    },
    {
      "input": "Grayhawk Golf Club",
      "city": "Scottsdale",
      "status": "miss",
      "slugsTried": [
        "grayhawkgolfclub.com",
        "grayhawkgolf.com",
        "grayhawkgolfcourse.com",
        "grayhawkcc.com",
        "grayhawk.com",
        "grayhawk-golf-club.com",
        "grayhawk-golf.com",
        "grayhawk-golf-course.com",
        "playgrayhawk.com",
        "golfgrayhawk.com",
        "grayhawkgolfclub.org",
        "grayhawkgolf.org",
        "grayhawk-golf-club.org",
        "grayhawkgolfclub.net"
      ]
    },
    {
      "input": "Greenfield Lakes Golf Course",
      "city": "Gilbert",
      "status": "miss",
      "slugsTried": [
        "greenfieldlakesgolfcourse.com",
        "greenfieldlakesgolf.com",
        "greenfieldlakesgolfclub.com",
        "greenfieldlakescc.com",
        "greenfieldlakes.com",
        "greenfield-lakes-golf-course.com",
        "greenfield-lakes-golf.com",
        "greenfield-lakes-golf-club.com",
        "playgreenfieldlakes.com",
        "playgreenfield-lakes.com",
        "golfgreenfieldlakes.com",
        "greenfieldlakesgolfcourse.org",
        "greenfieldlakesgolf.org",
        "greenfield-lakes-golf-course.org",
        "greenfieldlakesgolfcourse.net"
      ]
    },
    {
      "input": "Happy Trails Golf Club",
      "city": "Surprise",
      "status": "miss",
      "slugsTried": [
        "happytrailsgolfclub.com",
        "happytrailsgolf.com",
        "happytrailsgolfcourse.com",
        "happytrailscc.com",
        "happytrails.com",
        "happy-trails-golf-club.com",
        "happy-trails-golf.com",
        "happy-trails-golf-course.com",
        "playhappytrails.com",
        "playhappy-trails.com",
        "golfhappytrails.com",
        "happytrailsgolfclub.org",
        "happytrailsgolf.org",
        "happy-trails-golf-club.org",
        "happytrailsgolfclub.net"
      ]
    },
    {
      "input": "Hillcrest Golf Club",
      "city": "Sun City West",
      "status": "miss",
      "slugsTried": [
        "hillcrestgolfclub.com",
        "hillcrestgolf.com",
        "hillcrestgolfcourse.com",
        "hillcrestcc.com",
        "hillcrest.com",
        "hillcrest-golf-club.com",
        "hillcrest-golf.com",
        "hillcrest-golf-course.com",
        "playhillcrest.com",
        "golfhillcrest.com",
        "hillcrestgolfclub.org",
        "hillcrestgolf.org",
        "hillcrest-golf-club.org",
        "hillcrestgolfclub.net"
      ]
    },
    {
      "input": "InScape Golf",
      "city": "Mesa",
      "status": "miss",
      "slugsTried": [
        "inscapegolf.com",
        "inscapegolfgolf.com",
        "inscapegolfgolfclub.com",
        "inscapegolfgolfcourse.com",
        "inscapegolfcc.com",
        "inscape-golf.com",
        "inscape-golf-golf.com",
        "inscape-golf-golf-club.com",
        "inscape-golf-golf-course.com",
        "playinscapegolf.com",
        "playinscape-golf.com",
        "golfinscapegolf.com",
        "inscapegolf.org",
        "inscapegolfgolf.org",
        "inscape-golf.org",
        "inscapegolf.net"
      ]
    },
    {
      "input": "Ironwood Golf Course",
      "city": "Chandler",
      "status": "miss",
      "slugsTried": [
        "ironwoodgolfcourse.com",
        "ironwoodgolf.com",
        "ironwoodgolfclub.com",
        "ironwoodcc.com",
        "ironwood.com",
        "ironwood-golf-course.com",
        "ironwood-golf.com",
        "ironwood-golf-club.com",
        "playironwood.com",
        "golfironwood.com",
        "ironwoodgolfcourse.org",
        "ironwoodgolf.org",
        "ironwood-golf-course.org",
        "ironwoodgolfcourse.net"
      ]
    },
    {
      "input": "Kokopelli Golf Club",
      "city": "Gilbert",
      "status": "miss",
      "slugsTried": [
        "kokopelligolfclub.com",
        "kokopelligolf.com",
        "kokopelligolfcourse.com",
        "kokopellicc.com",
        "kokopelli.com",
        "kokopelli-golf-club.com",
        "kokopelli-golf.com",
        "kokopelli-golf-course.com",
        "playkokopelli.com",
        "golfkokopelli.com",
        "kokopelligolfclub.org",
        "kokopelligolf.org",
        "kokopelli-golf-club.org",
        "kokopelligolfclub.net"
      ]
    },
    {
      "input": "Las Colinas Golf Club",
      "city": "Queen Creek",
      "status": "miss",
      "slugsTried": [
        "lascolinasgolfclub.com",
        "lascolinasgolf.com",
        "lascolinasgolfcourse.com",
        "lascolinascc.com",
        "lascolinas.com",
        "las-colinas-golf-club.com",
        "las-colinas-golf.com",
        "las-colinas-golf-course.com",
        "playlascolinas.com",
        "playlas-colinas.com",
        "golflascolinas.com",
        "lascolinasgolfclub.org",
        "lascolinasgolf.org",
        "las-colinas-golf-club.org",
        "lascolinasgolfclub.net"
      ]
    },
    {
      "input": "Las Sendas Golf Club",
      "city": "Mesa",
      "status": "miss",
      "slugsTried": [
        "lassendasgolfclub.com",
        "lassendasgolf.com",
        "lassendasgolfcourse.com",
        "lassendascc.com",
        "lassendas.com",
        "las-sendas-golf-club.com",
        "las-sendas-golf.com",
        "las-sendas-golf-course.com",
        "playlassendas.com",
        "playlas-sendas.com",
        "golflassendas.com",
        "lassendasgolfclub.org",
        "lassendasgolf.org",
        "las-sendas-golf-club.org",
        "lassendasgolfclub.net"
      ]
    },
    {
      "input": "Legacy Golf Club",
      "city": "Phoenix",
      "status": "miss",
      "slugsTried": [
        "legacygolfclub.com",
        "legacygolf.com",
        "legacygolfcourse.com",
        "legacycc.com",
        "legacy.com",
        "legacy-golf-club.com",
        "legacy-golf.com",
        "legacy-golf-course.com",
        "playlegacy.com",
        "golflegacy.com",
        "legacygolfclub.org",
        "legacygolf.org",
        "legacy-golf-club.org",
        "legacygolfclub.net"
      ]
    },
    {
      "input": "Legend Trail Golf Club",
      "city": "Scottsdale",
      "status": "miss",
      "slugsTried": [
        "legendtrailgolfclub.com",
        "legendtrailgolf.com",
        "legendtrailgolfcourse.com",
        "legendtrailcc.com",
        "legendtrail.com",
        "legend-trail-golf-club.com",
        "legend-trail-golf.com",
        "legend-trail-golf-course.com",
        "playlegendtrail.com",
        "playlegend-trail.com",
        "golflegendtrail.com",
        "legendtrailgolfclub.org",
        "legendtrailgolf.org",
        "legend-trail-golf-club.org",
        "legendtrailgolfclub.net"
      ]
    },
    {
      "input": "Leisure World Golf Course",
      "city": "Mesa",
      "status": "miss",
      "slugsTried": [
        "leisureworldgolfcourse.com",
        "leisureworldgolf.com",
        "leisureworldgolfclub.com",
        "leisureworldcc.com",
        "leisureworld.com",
        "leisure-world-golf-course.com",
        "leisure-world-golf.com",
        "leisure-world-golf-club.com",
        "playleisureworld.com",
        "playleisure-world.com",
        "golfleisureworld.com",
        "leisureworldgolfcourse.org",
        "leisureworldgolf.org",
        "leisure-world-golf-course.org",
        "leisureworldgolfcourse.net"
      ]
    },
    {
      "input": "Lone Tree Golf Club",
      "city": "Chandler",
      "status": "listed_only",
      "websiteUrl": "https://www.lonetreegolfcourse.com",
      "server": 6,
      "apiKey": "hbiaeaab",
      "datesChecked": [
        "2026-02-18",
        "2026-02-14",
        "2026-02-21"
      ],
      "teeTimes": [
        0,
        0,
        0
      ]
    },
    {
      "input": "Longbow Golf Club",
      "city": "Mesa",
      "status": "miss",
      "slugsTried": [
        "longbowgolfclub.com",
        "longbowgolf.com",
        "longbowgolfcourse.com",
        "longbowcc.com",
        "longbow.com",
        "longbow-golf-club.com",
        "longbow-golf.com",
        "longbow-golf-course.com",
        "playlongbow.com",
        "golflongbow.com",
        "longbowgolfclub.org",
        "longbowgolf.org",
        "longbow-golf-club.org",
        "longbowgolfclub.net"
      ]
    },
    {
      "input": "Lookout Mountain Golf Club",
      "city": "Phoenix",
      "status": "miss",
      "slugsTried": [
        "lookoutmountaingolfclub.com",
        "lookoutmountaingolf.com",
        "lookoutmountaingolfcourse.com",
        "lookoutmountaincc.com",
        "lookoutmountain.com",
        "lookout-mountain-golf-club.com",
        "lookout-mountain-golf.com",
        "lookout-mountain-golf-course.com",
        "playlookoutmountain.com",
        "playlookout-mountain.com",
        "golflookoutmountain.com",
        "lookoutmountaingolfclub.org",
        "lookoutmountaingolf.org",
        "lookout-mountain-golf-club.org",
        "lookoutmountaingolfclub.net"
      ]
    },
    {
      "input": "Los Caballeros Golf Club",
      "city": "Wickenburg",
      "status": "miss",
      "slugsTried": [
        "loscaballerosgolfclub.com",
        "loscaballerosgolf.com",
        "loscaballerosgolfcourse.com",
        "loscaballeroscc.com",
        "loscaballeros.com",
        "los-caballeros-golf-club.com",
        "los-caballeros-golf.com",
        "los-caballeros-golf-course.com",
        "playloscaballeros.com",
        "playlos-caballeros.com",
        "golfloscaballeros.com",
        "loscaballerosgolfclub.org",
        "loscaballerosgolf.org",
        "los-caballeros-golf-club.org",
        "loscaballerosgolfclub.net"
      ]
    },
    {
      "input": "McCormick Ranch Golf Club",
      "city": "Scottsdale",
      "status": "miss",
      "slugsTried": [
        "mccormickranchgolfclub.com",
        "mccormickranchgolf.com",
        "mccormickranchgolfcourse.com",
        "mccormickranchcc.com",
        "mccormickranch.com",
        "mccormick-ranch-golf-club.com",
        "mccormick-ranch-golf.com",
        "mccormick-ranch-golf-course.com",
        "playmccormickranch.com",
        "playmccormick-ranch.com",
        "golfmccormickranch.com",
        "mccormickranchgolfclub.org",
        "mccormickranchgolf.org",
        "mccormick-ranch-golf-club.org",
        "mccormickranchgolfclub.net"
      ]
    },
    {
      "input": "McDowell Mountain Golf Club",
      "city": "Scottsdale",
      "status": "miss",
      "slugsTried": [
        "mcdowellmountaingolfclub.com",
        "mcdowellmountaingolf.com",
        "mcdowellmountaingolfcourse.com",
        "mcdowellmountaincc.com",
        "mcdowellmountain.com",
        "mcdowell-mountain-golf-club.com",
        "mcdowell-mountain-golf.com",
        "mcdowell-mountain-golf-course.com",
        "playmcdowellmountain.com",
        "playmcdowell-mountain.com",
        "golfmcdowellmountain.com",
        "mcdowellmountaingolfclub.org",
        "mcdowellmountaingolf.org",
        "mcdowell-mountain-golf-club.org",
        "mcdowellmountaingolfclub.net"
      ]
    },
    {
      "input": "Mountain Brook Golf Club",
      "city": "Gold Canyon",
      "status": "miss",
      "slugsTried": [
        "mountainbrookgolfclub.com",
        "mountainbrookgolf.com",
        "mountainbrookgolfcourse.com",
        "mountainbrookcc.com",
        "mountainbrook.com",
        "mountain-brook-golf-club.com",
        "mountain-brook-golf.com",
        "mountain-brook-golf-course.com",
        "playmountainbrook.com",
        "playmountain-brook.com",
        "golfmountainbrook.com",
        "mountainbrookgolfclub.org",
        "mountainbrookgolf.org",
        "mountain-brook-golf-club.org",
        "mountainbrookgolfclub.net"
      ]
    },
    {
      "input": "Ocotillo Golf Club",
      "city": "Chandler",
      "status": "miss",
      "slugsTried": [
        "ocotillogolfclub.com",
        "ocotillogolf.com",
        "ocotillogolfcourse.com",
        "ocotillocc.com",
        "ocotillo.com",
        "ocotillo-golf-club.com",
        "ocotillo-golf.com",
        "ocotillo-golf-course.com",
        "playocotillo.com",
        "golfocotillo.com",
        "ocotillogolfclub.org",
        "ocotillogolf.org",
        "ocotillo-golf-club.org",
        "ocotillogolfclub.net"
      ]
    },
    {
      "input": "Orange Tree Golf Course",
      "city": "Scottsdale",
      "status": "miss",
      "slugsTried": [
        "orangetreegolfcourse.com",
        "orangetreegolf.com",
        "orangetreegolfclub.com",
        "orangetreecc.com",
        "orangetree.com",
        "orange-tree-golf-course.com",
        "orange-tree-golf.com",
        "orange-tree-golf-club.com",
        "playorangetree.com",
        "playorange-tree.com",
        "golforangetree.com",
        "orangetreegolfcourse.org",
        "orangetreegolf.org",
        "orange-tree-golf-course.org",
        "orangetreegolfcourse.net"
      ]
    },
    {
      "input": "Painted Mountain Golf Resort",
      "city": "Mesa",
      "status": "miss",
      "slugsTried": [
        "paintedmountaingolfresort.com",
        "paintedmountaingolf.com",
        "paintedmountaingolfclub.com",
        "paintedmountaingolfcourse.com",
        "paintedmountaincc.com",
        "paintedmountain.com",
        "painted-mountain-golf-resort.com",
        "painted-mountain-golf.com",
        "painted-mountain-golf-club.com",
        "painted-mountain-golf-course.com",
        "playpaintedmountain.com",
        "playpainted-mountain.com",
        "golfpaintedmountain.com",
        "paintedmountaingolfresort.org",
        "paintedmountaingolf.org",
        "painted-mountain-golf-resort.org",
        "paintedmountaingolfresort.net"
      ]
    },
    {
      "input": "Palm Valley Golf Club",
      "city": "Goodyear",
      "status": "miss",
      "slugsTried": [
        "palmvalleygolfclub.com",
        "palmvalleygolf.com",
        "palmvalleygolfcourse.com",
        "palmvalleycc.com",
        "palmvalley.com",
        "palm-valley-golf-club.com",
        "palm-valley-golf.com",
        "palm-valley-golf-course.com",
        "playpalmvalley.com",
        "playpalm-valley.com",
        "golfpalmvalley.com",
        "palmvalleygolfclub.org",
        "palmvalleygolf.org",
        "palm-valley-golf-club.org",
        "palmvalleygolfclub.net"
      ]
    },
    {
      "input": "Paradise Valley Golf Course",
      "city": "Phoenix",
      "status": "miss",
      "slugsTried": [
        "paradisevalleygolfcourse.com",
        "paradisevalleygolf.com",
        "paradisevalleygolfclub.com",
        "paradisevalleycc.com",
        "paradisevalley.com",
        "paradise-valley-golf-course.com",
        "paradise-valley-golf.com",
        "paradise-valley-golf-club.com",
        "playparadisevalley.com",
        "playparadise-valley.com",
        "golfparadisevalley.com",
        "paradisevalleygolfcourse.org",
        "paradisevalleygolf.org",
        "paradise-valley-golf-course.org",
        "paradisevalleygolfcourse.net"
      ]
    },
    {
      "input": "Pueblo El Mirage Golf Course",
      "city": "El Mirage",
      "status": "miss",
      "slugsTried": [
        "puebloelmiragegolfcourse.com",
        "puebloelmiragegolf.com",
        "puebloelmiragegolfclub.com",
        "puebloelmiragecc.com",
        "puebloelmirage.com",
        "pueblo-el-mirage-golf-course.com",
        "pueblo-el-mirage-golf.com",
        "pueblo-el-mirage-golf-club.com",
        "playpuebloelmirage.com",
        "playpueblo-el-mirage.com",
        "golfpuebloelmirage.com",
        "puebloelmiragegolfcourse.org",
        "puebloelmiragegolf.org",
        "pueblo-el-mirage-golf-course.org",
        "puebloelmiragegolfcourse.net"
      ]
    },
    {
      "input": "Quintero Golf Club",
      "city": "Peoria",
      "status": "miss",
      "slugsTried": [
        "quinterogolfclub.com",
        "quinterogolf.com",
        "quinterogolfcourse.com",
        "quinterocc.com",
        "quintero.com",
        "quintero-golf-club.com",
        "quintero-golf.com",
        "quintero-golf-course.com",
        "playquintero.com",
        "golfquintero.com",
        "quinterogolfclub.org",
        "quinterogolf.org",
        "quintero-golf-club.org",
        "quinterogolfclub.net"
      ]
    },
    {
      "input": "Rancho Manana Golf Club",
      "city": "Cave Creek",
      "status": "miss",
      "slugsTried": [
        "ranchomananagolfclub.com",
        "ranchomananagolf.com",
        "ranchomananagolfcourse.com",
        "ranchomananacc.com",
        "ranchomanana.com",
        "rancho-manana-golf-club.com",
        "rancho-manana-golf.com",
        "rancho-manana-golf-course.com",
        "playranchomanana.com",
        "playrancho-manana.com",
        "golfranchomanana.com",
        "ranchomananagolfclub.org",
        "ranchomananagolf.org",
        "rancho-manana-golf-club.org",
        "ranchomananagolfclub.net"
      ]
    },
    {
      "input": "Raven Golf Club Phoenix",
      "city": "Phoenix",
      "status": "miss",
      "slugsTried": [
        "ravengolfclubphoenix.com",
        "ravenphoenixgolf.com",
        "ravenphoenixgolfclub.com",
        "ravenphoenixgolfcourse.com",
        "ravenphoenixcc.com",
        "ravenphoenix.com",
        "raven-golf-club-phoenix.com",
        "raven-phoenix-golf.com",
        "raven-phoenix-golf-club.com",
        "raven-phoenix-golf-course.com",
        "playravenphoenix.com",
        "playraven-phoenix.com",
        "golfravenphoenix.com",
        "ravengolfclubphoenix.org",
        "ravenphoenixgolf.org",
        "raven-golf-club-phoenix.org",
        "ravengolfclubphoenix.net"
      ]
    },
    {
      "input": "Red Mountain Ranch Country Club",
      "city": "Mesa",
      "status": "miss",
      "slugsTried": [
        "redmountainranchcountryclub.com",
        "redmountainranchgolf.com",
        "redmountainranchgolfclub.com",
        "redmountainranchgolfcourse.com",
        "redmountainranchcc.com",
        "redmountainranch.com",
        "red-mountain-ranch-country-club.com",
        "red-mountain-ranch-golf.com",
        "red-mountain-ranch-golf-club.com",
        "red-mountain-ranch-golf-course.com",
        "playredmountainranch.com",
        "playred-mountain-ranch.com",
        "golfredmountainranch.com",
        "redmountainranchcountryclub.org",
        "redmountainranchgolf.org",
        "red-mountain-ranch-country-club.org",
        "redmountainranchcountryclub.net"
      ]
    },
    {
      "input": "Riverview Golf Course",
      "city": "Mesa",
      "status": "miss",
      "slugsTried": [
        "riverviewgolfcourse.com",
        "riverviewgolf.com",
        "riverviewgolfclub.com",
        "riverviewcc.com",
        "riverview.com",
        "riverview-golf-course.com",
        "riverview-golf.com",
        "riverview-golf-club.com",
        "playriverview.com",
        "golfriverview.com",
        "riverviewgolfcourse.org",
        "riverviewgolf.org",
        "riverview-golf-course.org",
        "riverviewgolfcourse.net"
      ]
    },
    {
      "input": "Royal Palms Golf Course",
      "city": "Mesa",
      "status": "miss",
      "slugsTried": [
        "royalpalmsgolfcourse.com",
        "royalpalmsgolf.com",
        "royalpalmsgolfclub.com",
        "royalpalmscc.com",
        "royalpalms.com",
        "royal-palms-golf-course.com",
        "royal-palms-golf.com",
        "royal-palms-golf-club.com",
        "playroyalpalms.com",
        "playroyal-palms.com",
        "golfroyalpalms.com",
        "royalpalmsgolfcourse.org",
        "royalpalmsgolf.org",
        "royal-palms-golf-course.org",
        "royalpalmsgolfcourse.net"
      ]
    },
    {
      "input": "San Marcos Golf Course",
      "city": "Chandler",
      "status": "miss",
      "slugsTried": [
        "sanmarcosgolfcourse.com",
        "sanmarcosgolf.com",
        "sanmarcosgolfclub.com",
        "sanmarcoscc.com",
        "sanmarcos.com",
        "san-marcos-golf-course.com",
        "san-marcos-golf.com",
        "san-marcos-golf-club.com",
        "playsanmarcos.com",
        "playsan-marcos.com",
        "golfsanmarcos.com",
        "sanmarcosgolfcourse.org",
        "sanmarcosgolf.org",
        "san-marcos-golf-course.org",
        "sanmarcosgolfcourse.net"
      ]
    },
    {
      "input": "Scottsdale Silverado Golf Club",
      "city": "Scottsdale",
      "status": "miss",
      "slugsTried": [
        "scottsdalesilveradogolfclub.com",
        "scottsdalesilveradogolf.com",
        "scottsdalesilveradogolfcourse.com",
        "scottsdalesilveradocc.com",
        "scottsdalesilverado.com",
        "scottsdale-silverado-golf-club.com",
        "scottsdale-silverado-golf.com",
        "scottsdale-silverado-golf-course.com",
        "playscottsdalesilverado.com",
        "playscottsdale-silverado.com",
        "golfscottsdalesilverado.com",
        "scottsdalesilveradogolfclub.org",
        "scottsdalesilveradogolf.org",
        "scottsdale-silverado-golf-club.org",
        "scottsdalesilveradogolfclub.net"
      ]
    },
    {
      "input": "Shalimar Golf Club",
      "city": "Tempe",
      "status": "miss",
      "slugsTried": [
        "shalimargolfclub.com",
        "shalimargolf.com",
        "shalimargolfcourse.com",
        "shalimarcc.com",
        "shalimar.com",
        "shalimar-golf-club.com",
        "shalimar-golf.com",
        "shalimar-golf-course.com",
        "playshalimar.com",
        "golfshalimar.com",
        "shalimargolfclub.org",
        "shalimargolf.org",
        "shalimar-golf-club.org",
        "shalimargolfclub.net"
      ]
    },
    {
      "input": "Starfire Golf Club",
      "city": "Scottsdale",
      "status": "miss",
      "slugsTried": [
        "starfiregolfclub.com",
        "starfiregolf.com",
        "starfiregolfcourse.com",
        "starfirecc.com",
        "starfire.com",
        "starfire-golf-club.com",
        "starfire-golf.com",
        "starfire-golf-course.com",
        "playstarfire.com",
        "golfstarfire.com",
        "starfiregolfclub.org",
        "starfiregolf.org",
        "starfire-golf-club.org",
        "starfiregolfclub.net"
      ]
    },
    {
      "input": "Stonecreek Golf Club",
      "city": "Phoenix",
      "status": "miss",
      "slugsTried": [
        "stonecreekgolfclub.com",
        "stonecreekgolf.com",
        "stonecreekgolfcourse.com",
        "stonecreekcc.com",
        "stonecreek.com",
        "stonecreek-golf-club.com",
        "stonecreek-golf.com",
        "stonecreek-golf-course.com",
        "playstonecreek.com",
        "golfstonecreek.com",
        "stonecreekgolfclub.org",
        "stonecreekgolf.org",
        "stonecreek-golf-club.org",
        "stonecreekgolfclub.net"
      ]
    },
    {
      "input": "Sundance Golf Club",
      "city": "Buckeye",
      "status": "miss",
      "slugsTried": [
        "sundancegolfclub.com",
        "sundancegolf.com",
        "sundancegolfcourse.com",
        "sundancecc.com",
        "sundance.com",
        "sundance-golf-club.com",
        "sundance-golf.com",
        "sundance-golf-course.com",
        "playsundance.com",
        "golfsundance.com",
        "sundancegolfclub.org",
        "sundancegolf.org",
        "sundance-golf-club.org",
        "sundancegolfclub.net"
      ]
    },
    {
      "input": "SunRidge Canyon Golf Club",
      "city": "Fountain Hills",
      "status": "miss",
      "slugsTried": [
        "sunridgecanyongolfclub.com",
        "sunridgecanyongolf.com",
        "sunridgecanyongolfcourse.com",
        "sunridgecanyoncc.com",
        "sunridgecanyon.com",
        "sunridge-canyon-golf-club.com",
        "sunridge-canyon-golf.com",
        "sunridge-canyon-golf-course.com",
        "playsunridgecanyon.com",
        "playsunridge-canyon.com",
        "golfsunridgecanyon.com",
        "sunridgecanyongolfclub.org",
        "sunridgecanyongolf.org",
        "sunridge-canyon-golf-club.org",
        "sunridgecanyongolfclub.net"
      ]
    },
    {
      "input": "Sunland Springs Village Golf",
      "city": "Mesa",
      "status": "miss",
      "slugsTried": [
        "sunlandspringsvillagegolf.com",
        "sunlandspringsvillagegolfgolf.com",
        "sunlandspringsvillagegolfgolfclub.com",
        "sunlandspringsvillagegolfgolfcourse.com",
        "sunlandspringsvillagegolfcc.com",
        "sunland-springs-village-golf.com",
        "sunland-springs-village-golf-golf.com",
        "sunland-springs-village-golf-golf-club.com",
        "sunland-springs-village-golf-golf-course.com",
        "playsunlandspringsvillagegolf.com",
        "playsunland-springs-village-golf.com",
        "golfsunlandspringsvillagegolf.com",
        "sunlandspringsvillagegolf.org",
        "sunlandspringsvillagegolfgolf.org",
        "sunland-springs-village-golf.org",
        "sunlandspringsvillagegolf.net"
      ]
    },
    {
      "input": "Superstition Springs Golf Club",
      "city": "Mesa",
      "status": "miss",
      "slugsTried": [
        "superstitionspringsgolfclub.com",
        "superstitionspringsgolf.com",
        "superstitionspringsgolfcourse.com",
        "superstitionspringscc.com",
        "superstitionsprings.com",
        "superstition-springs-golf-club.com",
        "superstition-springs-golf.com",
        "superstition-springs-golf-course.com",
        "playsuperstitionsprings.com",
        "playsuperstition-springs.com",
        "golfsuperstitionsprings.com",
        "superstitionspringsgolfclub.org",
        "superstitionspringsgolf.org",
        "superstition-springs-golf-club.org",
        "superstitionspringsgolfclub.net"
      ]
    },
    {
      "input": "Talking Stick Golf Club",
      "city": "Scottsdale",
      "status": "miss",
      "slugsTried": [
        "talkingstickgolfclub.com",
        "talkingstickgolf.com",
        "talkingstickgolfcourse.com",
        "talkingstickcc.com",
        "talkingstick.com",
        "talking-stick-golf-club.com",
        "talking-stick-golf.com",
        "talking-stick-golf-course.com",
        "playtalkingstick.com",
        "playtalking-stick.com",
        "golftalkingstick.com",
        "talkingstickgolfclub.org",
        "talkingstickgolf.org",
        "talking-stick-golf-club.org",
        "talkingstickgolfclub.net"
      ]
    },
    {
      "input": "Tatum Ranch Golf Club",
      "city": "Cave Creek",
      "status": "miss",
      "slugsTried": [
        "tatumranchgolfclub.com",
        "tatumranchgolf.com",
        "tatumranchgolfcourse.com",
        "tatumranchcc.com",
        "tatumranch.com",
        "tatum-ranch-golf-club.com",
        "tatum-ranch-golf.com",
        "tatum-ranch-golf-course.com",
        "playtatumranch.com",
        "playtatum-ranch.com",
        "golftatumranch.com",
        "tatumranchgolfclub.org",
        "tatumranchgolf.org",
        "tatum-ranch-golf-club.org",
        "tatumranchgolfclub.net"
      ]
    },
    {
      "input": "The Phoenician Golf Club",
      "city": "Scottsdale",
      "status": "miss",
      "slugsTried": [
        "thephoeniciangolfclub.com",
        "phoeniciangolf.com",
        "phoeniciangolfclub.com",
        "phoeniciangolfcourse.com",
        "phoeniciancc.com",
        "phoenician.com",
        "phoeniciangolfclubgolf.com",
        "the-phoenician-golf-club.com",
        "phoenician-golf.com",
        "phoenician-golf-club.com",
        "phoenician-golf-course.com",
        "playphoenician.com",
        "golfphoenician.com",
        "thephoeniciangolfclub.org",
        "phoeniciangolf.org",
        "the-phoenician-golf-club.org",
        "thephoeniciangolfclub.net"
      ]
    },
    {
      "input": "TPC Scottsdale",
      "city": "Scottsdale",
      "status": "miss",
      "slugsTried": [
        "tpcscottsdale.com",
        "tpcscottsdalegolf.com",
        "tpcscottsdalegolfclub.com",
        "tpcscottsdalegolfcourse.com",
        "tpcscottsdalecc.com",
        "tpc-scottsdale.com",
        "tpc-scottsdale-golf.com",
        "tpc-scottsdale-golf-club.com",
        "tpc-scottsdale-golf-course.com",
        "playtpcscottsdale.com",
        "playtpc-scottsdale.com",
        "golftpcscottsdale.com",
        "tpcscottsdale.org",
        "tpcscottsdalegolf.org",
        "tpc-scottsdale.org",
        "tpcscottsdale.net"
      ]
    },
    {
      "input": "Tres Rios Golf Course",
      "city": "Goodyear",
      "status": "miss",
      "slugsTried": [
        "tresriosgolfcourse.com",
        "tresriosgolf.com",
        "tresriosgolfclub.com",
        "tresrioscc.com",
        "tresrios.com",
        "tres-rios-golf-course.com",
        "tres-rios-golf.com",
        "tres-rios-golf-club.com",
        "playtresrios.com",
        "playtres-rios.com",
        "golftresrios.com",
        "tresriosgolfcourse.org",
        "tresriosgolf.org",
        "tres-rios-golf-course.org",
        "tresriosgolfcourse.net"
      ]
    },
    {
      "input": "Trilogy Golf Club at Vistancia",
      "city": "Peoria",
      "status": "miss",
      "slugsTried": [
        "trilogygolfclubatvistancia.com",
        "trilogyatvistanciagolf.com",
        "trilogyatvistanciagolfclub.com",
        "trilogyatvistanciagolfcourse.com",
        "trilogyatvistanciacc.com",
        "trilogyatvistancia.com",
        "trilogy-golf-club-at-vistancia.com",
        "trilogy-at-vistancia-golf.com",
        "trilogy-at-vistancia-golf-club.com",
        "trilogy-at-vistancia-golf-course.com",
        "playtrilogyatvistancia.com",
        "playtrilogy-at-vistancia.com",
        "golftrilogyatvistancia.com",
        "trilogygolfclubatvistancia.org",
        "trilogyatvistanciagolf.org",
        "trilogy-golf-club-at-vistancia.org",
        "trilogygolfclubatvistancia.net"
      ]
    },
    {
      "input": "Troon North Golf Club",
      "city": "Scottsdale",
      "status": "miss",
      "slugsTried": [
        "troonnorthgolfclub.com",
        "troonnorthgolf.com",
        "troonnorthgolfcourse.com",
        "troonnorthcc.com",
        "troonnorth.com",
        "troon-north-golf-club.com",
        "troon-north-golf.com",
        "troon-north-golf-course.com",
        "playtroonnorth.com",
        "playtroon-north.com",
        "golftroonnorth.com",
        "troonnorthgolfclub.org",
        "troonnorthgolf.org",
        "troon-north-golf-club.org",
        "troonnorthgolfclub.net"
      ]
    },
    {
      "input": "Verde River Golf Club",
      "city": "Rio Verde",
      "status": "miss",
      "slugsTried": [
        "verderivergolfclub.com",
        "verderivergolf.com",
        "verderivergolfcourse.com",
        "verderivercc.com",
        "verderiver.com",
        "verde-river-golf-club.com",
        "verde-river-golf.com",
        "verde-river-golf-course.com",
        "playverderiver.com",
        "playverde-river.com",
        "golfverderiver.com",
        "verderivergolfclub.org",
        "verderivergolf.org",
        "verde-river-golf-club.org",
        "verderivergolfclub.net"
      ]
    },
    {
      "input": "Verrado Golf Club",
      "city": "Buckeye",
      "status": "miss",
      "slugsTried": [
        "verradogolfclub.com",
        "verradogolf.com",
        "verradogolfcourse.com",
        "verradocc.com",
        "verrado.com",
        "verrado-golf-club.com",
        "verrado-golf.com",
        "verrado-golf-course.com",
        "playverrado.com",
        "golfverrado.com",
        "verradogolfclub.org",
        "verradogolf.org",
        "verrado-golf-club.org",
        "verradogolfclub.net"
      ]
    },
    {
      "input": "Viewpoint Golf Resort",
      "city": "Mesa",
      "status": "miss",
      "slugsTried": [
        "viewpointgolfresort.com",
        "viewpointgolf.com",
        "viewpointgolfclub.com",
        "viewpointgolfcourse.com",
        "viewpointcc.com",
        "viewpoint.com",
        "viewpoint-golf-resort.com",
        "viewpoint-golf.com",
        "viewpoint-golf-club.com",
        "viewpoint-golf-course.com",
        "playviewpoint.com",
        "golfviewpoint.com",
        "viewpointgolfresort.org",
        "viewpointgolf.org",
        "viewpoint-golf-resort.org",
        "viewpointgolfresort.net"
      ]
    },
    {
      "input": "We-Ko-Pa Golf Club",
      "city": "Fort McDowell",
      "status": "miss",
      "slugsTried": [
        "wekopagolfclub.com",
        "wekopagolf.com",
        "wekopagolfcourse.com",
        "wekopacc.com",
        "wekopa.com",
        "we-ko-pa-golf-club.com",
        "we-ko-pa-golf.com",
        "we-ko-pa-golf-course.com",
        "playwekopa.com",
        "playwe-ko-pa.com",
        "golfwekopa.com",
        "wekopagolfclub.org",
        "wekopagolf.org",
        "we-ko-pa-golf-club.org",
        "wekopagolfclub.net"
      ]
    },
    {
      "input": "Westin Kierland Golf Club",
      "city": "Scottsdale",
      "status": "miss",
      "slugsTried": [
        "westinkierlandgolfclub.com",
        "westinkierlandgolf.com",
        "westinkierlandgolfcourse.com",
        "westinkierlandcc.com",
        "westinkierland.com",
        "westin-kierland-golf-club.com",
        "westin-kierland-golf.com",
        "westin-kierland-golf-course.com",
        "playwestinkierland.com",
        "playwestin-kierland.com",
        "golfwestinkierland.com",
        "westinkierlandgolfclub.org",
        "westinkierlandgolf.org",
        "westin-kierland-golf-club.org",
        "westinkierlandgolfclub.net"
      ]
    },
    {
      "input": "Westbrook Village Golf Club",
      "city": "Peoria",
      "status": "miss",
      "slugsTried": [
        "westbrookvillagegolfclub.com",
        "westbrookvillagegolf.com",
        "westbrookvillagegolfcourse.com",
        "westbrookvillagecc.com",
        "westbrookvillage.com",
        "westbrook-village-golf-club.com",
        "westbrook-village-golf.com",
        "westbrook-village-golf-course.com",
        "playwestbrookvillage.com",
        "playwestbrook-village.com",
        "golfwestbrookvillage.com",
        "westbrookvillagegolfclub.org",
        "westbrookvillagegolf.org",
        "westbrook-village-golf-club.org",
        "westbrookvillagegolfclub.net"
      ]
    },
    {
      "input": "Whirlwind Golf Club",
      "city": "Chandler",
      "status": "miss",
      "slugsTried": [
        "whirlwindgolfclub.com",
        "whirlwindgolf.com",
        "whirlwindgolfcourse.com",
        "whirlwindcc.com",
        "whirlwind.com",
        "whirlwind-golf-club.com",
        "whirlwind-golf.com",
        "whirlwind-golf-course.com",
        "playwhirlwind.com",
        "golfwhirlwind.com",
        "whirlwindgolfclub.org",
        "whirlwindgolf.org",
        "whirlwind-golf-club.org",
        "whirlwindgolfclub.net"
      ]
    },
    {
      "input": "Wickenburg Ranch Golf Club",
      "city": "Wickenburg",
      "status": "miss",
      "slugsTried": [
        "wickenburgranchgolfclub.com",
        "wickenburgranchgolf.com",
        "wickenburgranchgolfcourse.com",
        "wickenburgranchcc.com",
        "wickenburgranch.com",
        "wickenburg-ranch-golf-club.com",
        "wickenburg-ranch-golf.com",
        "wickenburg-ranch-golf-course.com",
        "playwickenburgranch.com",
        "playwickenburg-ranch.com",
        "golfwickenburgranch.com",
        "wickenburgranchgolfclub.org",
        "wickenburgranchgolf.org",
        "wickenburg-ranch-golf-club.org",
        "wickenburgranchgolfclub.net"
      ]
    },
    {
      "input": "Wickenburg Country Club",
      "city": "Wickenburg",
      "status": "miss",
      "slugsTried": [
        "wickenburgcountryclub.com",
        "wickenburggolf.com",
        "wickenburggolfclub.com",
        "wickenburggolfcourse.com",
        "wickenburgcc.com",
        "wickenburg.com",
        "wickenburg-country-club.com",
        "wickenburg-golf.com",
        "wickenburg-golf-club.com",
        "wickenburg-golf-course.com",
        "playwickenburg.com",
        "golfwickenburg.com",
        "wickenburgcountryclub.org",
        "wickenburggolf.org",
        "wickenburg-country-club.org",
        "wickenburgcountryclub.net"
      ]
    },
    {
      "input": "Wigwam Golf Club",
      "city": "Litchfield Park",
      "status": "miss",
      "slugsTried": [
        "wigwamgolfclub.com",
        "wigwamgolf.com",
        "wigwamgolfcourse.com",
        "wigwamcc.com",
        "wigwam.com",
        "wigwam-golf-club.com",
        "wigwam-golf.com",
        "wigwam-golf-course.com",
        "playwigwam.com",
        "golfwigwam.com",
        "wigwamgolfclub.org",
        "wigwamgolf.org",
        "wigwam-golf-club.org",
        "wigwamgolfclub.net"
      ]
    },
    {
      "input": "Wildfire Golf Club",
      "city": "Phoenix",
      "status": "miss",
      "slugsTried": [
        "wildfiregolfclub.com",
        "wildfiregolf.com",
        "wildfiregolfcourse.com",
        "wildfirecc.com",
        "wildfire.com",
        "wildfire-golf-club.com",
        "wildfire-golf.com",
        "wildfire-golf-course.com",
        "playwildfire.com",
        "golfwildfire.com",
        "wildfiregolfclub.org",
        "wildfiregolf.org",
        "wildfire-golf-club.org",
        "wildfiregolfclub.net"
      ]
    },
    {
      "input": "Alta Mesa Golf Club",
      "city": "Mesa",
      "status": "miss",
      "slugsTried": [
        "altamesagolfclub.com",
        "altamesagolf.com",
        "altamesagolfcourse.com",
        "altamesacc.com",
        "altamesa.com",
        "alta-mesa-golf-club.com",
        "alta-mesa-golf.com",
        "alta-mesa-golf-course.com",
        "playaltamesa.com",
        "playalta-mesa.com",
        "golfaltamesa.com",
        "altamesagolfclub.org",
        "altamesagolf.org",
        "alta-mesa-golf-club.org",
        "altamesagolfclub.net"
      ]
    },
    {
      "input": "Encanterra Country Club",
      "city": "Queen Creek",
      "status": "miss",
      "slugsTried": [
        "encanterracountryclub.com",
        "encanterragolf.com",
        "encanterragolfclub.com",
        "encanterragolfcourse.com",
        "encanterracc.com",
        "encanterra.com",
        "encanterra-country-club.com",
        "encanterra-golf.com",
        "encanterra-golf-club.com",
        "encanterra-golf-course.com",
        "playencanterra.com",
        "golfencanterra.com",
        "encanterracountryclub.org",
        "encanterragolf.org",
        "encanterra-country-club.org",
        "encanterracountryclub.net"
      ]
    },
    {
      "input": "Queen Valley Golf Course",
      "city": "Queen Valley",
      "status": "miss",
      "slugsTried": [
        "queenvalleygolfcourse.com",
        "queenvalleygolf.com",
        "queenvalleygolfclub.com",
        "queenvalleycc.com",
        "queenvalley.com",
        "queen-valley-golf-course.com",
        "queen-valley-golf.com",
        "queen-valley-golf-club.com",
        "playqueenvalley.com",
        "playqueen-valley.com",
        "golfqueenvalley.com",
        "queenvalleygolfcourse.org",
        "queenvalleygolf.org",
        "queen-valley-golf-course.org",
        "queenvalleygolfcourse.net"
      ]
    },
    {
      "input": "Springfield Golf Resort",
      "city": "Chandler",
      "status": "miss",
      "slugsTried": [
        "springfieldgolfresort.com",
        "springfieldgolf.com",
        "springfieldgolfclub.com",
        "springfieldgolfcourse.com",
        "springfieldcc.com",
        "springfield.com",
        "springfield-golf-resort.com",
        "springfield-golf.com",
        "springfield-golf-club.com",
        "springfield-golf-course.com",
        "playspringfield.com",
        "golfspringfield.com",
        "springfieldgolfresort.org",
        "springfieldgolf.org",
        "springfield-golf-resort.org",
        "springfieldgolfresort.net"
      ]
    }
  ],
  "state": "AZ",
  "timestamp": "2026-02-14T06:01:57-07:00",
  "total": 92
}