{
  "confirmed": 0,
  "elapsed": "35.051283375s",
  "listedOnly": 0,
  "misses": 28,
  "platform": "cpsgolf",
  "results": [
    {
      "input": "Charleston Municipal Golf Course",
      "city": "Charleston",
      "status": "miss",
      "slugsTried": [
        "charlestonmunicipal",
        "charlestonmunicipalgolfcourse",
        "charlestonmunicipalgolf",
        "charlestonmunicipalgolfclub",
        "charlestonmunicipalcc",
        "charleston-municipal",
        "charlestonmunicipalcharleston",
        "charleston-municipal-golf-course"
      ]
    },
    {
      "input": "Shadowmoss Plantation Golf Club",
      "city": "Charleston",
      "status": "miss",
      "slugsTried": [
        "shadowmossplantation",
        "shadowmossplantationgolfclub",
        "shadowmossplantationgolf",
        "shadowmossplantationgolfcourse",
        "shadowmossplantationcc",
        "shadowmoss-plantation",
        "shadowmossplantationcharleston",
        "shadowmoss-plantation-golf-club"
      ]
    },
    {
      "input": "Patriots Point Links",
      "city": "Mount Pleasant",
      "status": "miss",
      "slugsTried": [
        "patriotspointlinks",
        "patriotspointlinksgolf",
        "patriotspointlinksgolfclub",
        "patriotspointlinksgolfcourse",
        "patriotspointlinkscc",
        "patriots-point-links",
        "patriotspointlinksmountpleasant"
      ]
    },
    {
      "input": "Charleston National Golf Club",
      "city": "Mount Pleasant",
      "status": "miss",
      "slugsTried": [
        "charlestonnational",
        "charlestonnationalgolfclub",
        "charlestonnationalgolf",
        "charlestonnationalgolfcourse",
        "charlestonnationalcc",
        "charleston-national",
        "charlestonnationalmountpleasant",
        "charleston-national-golf-club"
      ]
    },
    {
      "input": "Dunes West Golf Club",
      "city": "Mount Pleasant",
      "status": "miss",
      "slugsTried": [
        "duneswest",
        "duneswestgolfclub",
        "duneswestgolf",
        "duneswestgolfcourse",
        "duneswestcc",
        "dunes-west",
        "duneswestmountpleasant",
        "dunes-west-golf-club"
      ]
    },
    {
      "input": "RiverTowne Country Club",
      "city": "Mount Pleasant",
      "status": "miss",
      "slugsTried": [
        "rivertowne",
        "rivertownecountryclub",
        "rivertownegolf",
        "rivertownegolfclub",
        "rivertownegolfcourse",
        "rivertownecc",
        "rivertownemountpleasant",
        "rivertowne-country-club"
      ]
    },
    {
      "input": "Wild Dunes Resort - Links Course",
      "city": "Isle of Palms",
      "status": "miss",
      "slugsTried": [
        "wilddunesresortlinkscourse",
        "wilddunesresortlinkscoursegolf",
        "wilddunesresortlinkscoursegolfclub",
        "wilddunesresortlinkscoursegolfcourse",
        "wilddunesresortlinkscoursecc",
        "wild-dunes-resort---links-course",
        "wilddunesresort",
        "wilddunesresortgolf",
        "wilddunesresortgolfclub",
        "wilddunesresortgolfcourse",
        "wilddunesresortlinkscourseisleofpalms",
        "wilddunesresortisleofpalms"
      ]
    },
    {
      "input": "Wild Dunes Resort - Harbor Course",
      "city": "Isle of Palms",
      "status": "miss",
      "slugsTried": [
        "wilddunesresortharborcourse",
        "wilddunesresortharborcoursegolf",
        "wilddunesresortharborcoursegolfclub",
        "wilddunesresortharborcoursegolfcourse",
        "wilddunesresortharborcoursecc",
        "wild-dunes-resort---harbor-course",
        "wilddunesresort",
        "wilddunesresortgolf",
        "wilddunesresortgolfclub",
        "wilddunesresortgolfcourse",
        "wilddunesresortharborcourseisleofpalms",
        "wilddunesresortisleofpalms"
      ]
    },
    {
      "input": "Coosaw Creek Country Club",
      "city": "North Charleston",
      "status": "miss",
      "slugsTried": [
        "coosawcreek",
        "coosawcreekcountryclub",
        "coosawcreekgolf",
        "coosawcreekgolfclub",
        "coosawcreekgolfcourse",
        "coosawcreekcc",
        "coosaw-creek",
        "coosawcreeknorthcharleston",
        "coosaw-creek-country-club"
      ]
    },
    {
      "input": "Eagle Landing Golf Club",
      "city": "Hanahan",
      "status": "miss",
      "slugsTried": [
        "eaglelanding",
        "eaglelandinggolfclub",
        "eaglelandinggolf",
        "eaglelandinggolfcourse",
        "eaglelandingcc",
        "eagle-landing",
        "eaglelandinghanahan",
        "eagle-landing-golf-club"
      ]
    },
    {
      "input": "Wrenwoods Golf Course",
      "city": "Joint Base Charleston",
      "status": "miss",
      "slugsTried": [
        "wrenwoods",
        "wrenwoodsgolfcourse",
        "wrenwoodsgolf",
        "wrenwoodsgolfclub",
        "wrenwoodscc",
        "wrenwoodsjointbasecharleston",
        "wrenwoods-golf-course"
      ]
    },
    {
      "input": "Crowfield Golf and Country Club",
      "city": "Goose Creek",
      "status": "miss",
      "slugsTried": [
        "crowfieldgolfand",
        "crowfieldgolfandcountryclub",
        "crowfieldgolfandgolf",
        "crowfieldgolfandgolfclub",
        "crowfieldgolfandgolfcourse",
        "crowfieldgolfandcc",
        "crowfieldgolfcountryclub",
        "crowfieldgolf",
        "crowfield-golf-and",
        "crowfieldgolfandgoosecreek",
        "crowfield-golf-and-country-club"
      ]
    },
    {
      "input": "The Oaks Golf and Country Club",
      "city": "Goose Creek",
      "status": "miss",
      "slugsTried": [
        "oaksgolfand",
        "theoaksgolfandcountryclub",
        "oaksgolfandgolf",
        "oaksgolfandgolfclub",
        "oaksgolfandgolfcourse",
        "oaksgolfandcc",
        "theoaksgolfcountryclub",
        "oaksgolf",
        "oaksgolfandcountryclub",
        "oaks-golf-and",
        "oaksgolfandgoosecreek",
        "the-oaks-golf-and-country-club"
      ]
    },
    {
      "input": "Redbank Plantation Golf Course",
      "city": "Goose Creek",
      "status": "miss",
      "slugsTried": [
        "redbankplantation",
        "redbankplantationgolfcourse",
        "redbankplantationgolf",
        "redbankplantationgolfclub",
        "redbankplantationcc",
        "redbank-plantation",
        "redbankplantationgoosecreek",
        "redbank-plantation-golf-course"
      ]
    },
    {
      "input": "Legend Oaks Golf Club",
      "city": "Summerville",
      "status": "miss",
      "slugsTried": [
        "legendoaks",
        "legendoaksgolfclub",
        "legendoaksgolf",
        "legendoaksgolfcourse",
        "legendoakscc",
        "legend-oaks",
        "legendoakssummerville",
        "legend-oaks-golf-club"
      ]
    },
    {
      "input": "The Golf Club at Wescott Plantation",
      "city": "Summerville",
      "status": "miss",
      "slugsTried": [
        "golfclubatwescottplantation",
        "thegolfclubatwescottplantation",
        "golfclubatwescottplantationgolf",
        "golfclubatwescottplantationgolfclub",
        "golfclubatwescottplantationgolfcourse",
        "golfclubatwescottplantationcc",
        "golf-club-at-wescott-plantation",
        "golfclubatwescottplantationsummerville",
        "the-golf-club-at-wescott-plantation"
      ]
    },
    {
      "input": "Summerville Country Club",
      "city": "Summerville",
      "status": "miss",
      "slugsTried": [
        "summerville",
        "summervillecountryclub",
        "summervillegolf",
        "summervillegolfclub",
        "summervillegolfcourse",
        "summervillecc",
        "summervillesummerville",
        "summerville-country-club"
      ]
    },
    {
      "input": "Pine Forest Country Club",
      "city": "Summerville",
      "status": "miss",
      "slugsTried": [
        "pineforest",
        "pineforestcountryclub",
        "pineforestgolf",
        "pineforestgolfclub",
        "pineforestgolfcourse",
        "pineforestcc",
        "pine-forest",
        "pineforestsummerville",
        "pine-forest-country-club"
      ]
    },
    {
      "input": "Berkeley Country Club",
      "city": "Moncks Corner",
      "status": "miss",
      "slugsTried": [
        "berkeley",
        "berkeleycountryclub",
        "berkeleygolf",
        "berkeleygolfclub",
        "berkeleygolfcourse",
        "berkeleycc",
        "berkeleymonckscorner",
        "berkeley-country-club"
      ]
    },
    {
      "input": "The Links at Stono Ferry",
      "city": "Hollywood",
      "status": "miss",
      "slugsTried": [
        "linksatstonoferry",
        "thelinksatstonoferry",
        "linksatstonoferrygolf",
        "linksatstonoferrygolfclub",
        "linksatstonoferrygolfcourse",
        "linksatstonoferrycc",
        "links-at-stono-ferry",
        "linksatstonoferryhollywood",
        "the-links-at-stono-ferry"
      ]
    },
    {
      "input": "Oak Point Golf Course",
      "city": "Johns Island",
      "status": "miss",
      "slugsTried": [
        "oakpoint",
        "oakpointgolfcourse",
        "oakpointgolf",
        "oakpointgolfclub",
        "oakpointcc",
        "oak-point",
        "oakpointjohnsisland",
        "oak-point-golf-course"
      ]
    },
    {
      "input": "Kiawah Island Resort - Ocean Course",
      "city": "Kiawah Island",
      "status": "miss",
      "slugsTried": [
        "kiawahislandresortoceancourse",
        "kiawahislandresortoceancoursegolf",
        "kiawahislandresortoceancoursegolfclub",
        "kiawahislandresortoceancoursegolfcourse",
        "kiawahislandresortoceancoursecc",
        "kiawah-island-resort---ocean-course",
        "kiawahislandresort",
        "kiawahislandresortgolf",
        "kiawahislandresortgolfclub",
        "kiawahislandresortgolfcourse",
        "kiawahislandresortoceancoursekiawahisland",
        "kiawahislandresortkiawahisland"
      ]
    },
    {
      "input": "Kiawah Island Resort - Osprey Point",
      "city": "Kiawah Island",
      "status": "miss",
      "slugsTried": [
        "kiawahislandresortospreypoint",
        "kiawahislandresortospreypointgolf",
        "kiawahislandresortospreypointgolfclub",
        "kiawahislandresortospreypointgolfcourse",
        "kiawahislandresortospreypointcc",
        "kiawah-island-resort---osprey-point",
        "kiawahislandresort",
        "kiawahislandresortgolf",
        "kiawahislandresortgolfclub",
        "kiawahislandresortgolfcourse",
        "kiawahislandresortospreypointkiawahisland",
        "kiawahislandresortkiawahisland"
      ]
    },
    {
      "input": "Kiawah Island Resort - Turtle Point",
      "city": "Kiawah Island",
      "status": "miss",
      "slugsTried": [
        "kiawahislandresortturtlepoint",
        "kiawahislandresortturtlepointgolf",
        "kiawahislandresortturtlepointgolfclub",
        "kiawahislandresortturtlepointgolfcourse",
        "kiawahislandresortturtlepointcc",
        "kiawah-island-resort---turtle-point",
        "kiawahislandresort",
        "kiawahislandresortgolf",
        "kiawahislandresortgolfclub",
        "kiawahislandresortgolfcourse",
        "kiawahislandresortturtlepointkiawahisland",
        "kiawahislandresortkiawahisland"
      ]
    },
    {
      "input": "Kiawah Island Resort - Cougar Point",
      "city": "Kiawah Island",
      "status": "miss",
      "slugsTried": [
        "kiawahislandresortcougarpoint",
        "kiawahislandresortcougarpointgolf",
        "kiawahislandresortcougarpointgolfclub",
        "kiawahislandresortcougarpointgolfcourse",
        "kiawahislandresortcougarpointcc",
        "kiawah-island-resort---cougar-point",
        "kiawahislandresort",
        "kiawahislandresortgolf",
        "kiawahislandresortgolfclub",
        "kiawahislandresortgolfcourse",
        "kiawahislandresortcougarpointkiawahisland",
        "kiawahislandresortkiawahisland"
      ]
    },
    {
      "input": "Seabrook Island Club - Crooked Oaks",
      "city": "Seabrook Island",
      "status": "miss",
      "slugsTried": [
        "seabrookislandclubcrookedoaks",
        "seabrookislandclubcrookedoaksgolf",
        "seabrookislandclubcrookedoaksgolfclub",
        "seabrookislandclubcrookedoaksgolfcourse",
        "seabrookislandclubcrookedoakscc",
        "seabrook-island-club---crooked-oaks",
        "seabrookislandclub",
        "seabrookislandclubgolf",
        "seabrookislandclubgolfclub",
        "seabrookislandclubgolfcourse",
        "seabrookislandclubcrookedoaksseabrookisland",
        "seabrookislandclubseabrookisland"
      ]
    },
    {
      "input": "Seabrook Island Club - Ocean Winds",
      "city": "Seabrook Island",
      "status": "miss",
      "slugsTried": [
        "seabrookislandcluboceanwinds",
        "seabrookislandcluboceanwindsgolf",
        "seabrookislandcluboceanwindsgolfclub",
        "seabrookislandcluboceanwindsgolfcourse",
        "seabrookislandcluboceanwindscc",
        "seabrook-island-club---ocean-winds",
        "seabrookislandclub",
        "seabrookislandclubgolf",
        "seabrookislandclubgolfclub",
        "seabrookislandclubgolfcourse",
        "seabrookislandcluboceanwindsseabrookisland",
        "seabrookislandclubseabrookisland"
      ]
    },
    {
      "input": "The Plantation Course at Edisto",
      "city": "Edisto Island",
      "status": "miss",
      "slugsTried": [
        "plantationcourseatedisto",
        "theplantationcourseatedisto",
        "plantationcourseatedistogolf",
        "plantationcourseatedistogolfclub",
        "plantationcourseatedistogolfcourse",
        "plantationcourseatedistocc",
        "plantation-course-at-edisto",
        "plantationcourseatedistoedistoisland",
        "the-plantation-course-at-edisto"
      ]
    }
  ],
  "state": "SC",
  "timestamp": "2026-03-06T07:22:08-07:00",
  "total": 28,
  "wrongState": 0
}